{
  "unversionedId": "Using Conply/Creating Account",
  "id": "version-1.1.0/Using Conply/Creating Account",
  "title": "Creating Account",
  "description": "",
  "source": "@site/versioned_docs/version-1.1.0/Using Conply/Creating Account.md",
  "sourceDirName": "Using Conply",
  "slug": "/Using Conply/Creating Account",
  "permalink": "/alsys-admin-playbook/Using Conply/Creating Account",
  "draft": false,
  "tags": [],
  "version": "1.1.0",
  "frontMatter": {},
  "sidebar": "tutorialSidebar",
  "previous": {
    "title": "Using Conply",
    "permalink": "/alsys-admin-playbook/category/using-conply"
  },
  "next": {
    "title": "User management",
    "permalink": "/alsys-admin-playbook/Using Conply/User management"
  }
}